Metadata-Version: 1.1
Name: engineio-client
Version: 0.2
Summary: Engine.IO client
Home-page: http://github.com/PeterWunderlich/python-engineio-client/
Author: Peter Wunderlich
Author-email: frederic.sureau@veo-labs.com
License: MIT
Platform: any
Classifier: Environment :: Web Environment
Classifier: Intended Audience :: Developers
Classifier: License :: OSI Approved :: MIT License
Classifier: Operating System :: OS Independent
Classifier: Programming Language :: Python
Classifier: Programming Language :: Python :: 2
Classifier: Programming Language :: Python :: 3
Classifier: Topic :: Internet :: WWW/HTTP :: Dynamic Content
Classifier: Topic :: Software Development :: Libraries :: Python Modules
